genome_circos/__init__.py
genome_circos/chr_circos.py
genome_circos-0.0.3.dist-info/LICENSE
genome_circos-0.0.3.dist-info/METADATA
genome_circos-0.0.3.dist-info/WHEEL
genome_circos-0.0.3.dist-info/RECORD
