Metadata-Version: 2.1
Name: genome-circos
Version: 0.0.3
Summary: Genome circos python package.
Home-page: https://github.com/wenlinXu-njfu/GenomeCircos
License: MIT
Author: Wenlin Xu
Author-email: wenlinxu.njfu@outlook.com
Requires-Python: >=3.8
Classifier: License :: OSI Approved :: MIT License
Classifier: Programming Language :: Python :: 3
Classifier: Programming Language :: Python :: 3.8
Classifier: Programming Language :: Python :: 3.9
Classifier: Programming Language :: Python :: 3.10
Classifier: Programming Language :: Python :: 3.11
Classifier: Programming Language :: Python :: 3.12
Classifier: Programming Language :: Python :: 3.13
Requires-Dist: matplotlib (>=3.7.5)
Requires-Dist: pandas (>=2.0.3)
